financial_statement/__init__.py
financial_statement/financial_statement.py
financial_statement-0.1.2.dist-info/LICENSE.rtf
financial_statement-0.1.2.dist-info/METADATA
financial_statement-0.1.2.dist-info/WHEEL
financial_statement-0.1.2.dist-info/top_level.txt
financial_statement-0.1.2.dist-info/RECORD
