Metadata-Version: 2.1
Name: financial_statement
Version: 0.1.2
Summary: Read the financial statement of listed company
Author: Ng wen kang
Author-email: kangwen177@gmail.com
Keywords: python,finance,financial statement,stock market
Classifier: Development Status :: 1 - Planning
Classifier: Intended Audience :: Developers
Classifier: Programming Language :: Python :: 3
Classifier: Operating System :: Unix
Classifier: Operating System :: MacOS :: MacOS X
Classifier: Operating System :: Microsoft :: Windows
License-File: LICENSE.rtf
Requires-Dist: requests
Requires-Dist: numpy
Requires-Dist: bs4
Requires-Dist: pandas
Requires-Dist: datetime
